xrocket/__init__.py
xrocket/_pay.py
xrocket/_trade.py
xrocket/pay/__init__.py
xrocket/pay/app.py
xrocket/pay/currencies.py
xrocket/pay/invoice.py
xrocket/pay/multi_cheque.py
xrocket/pay/subscription.py
xrocket/trade/__init__.py
xrocket/trade/account.py
xrocket/trade/order_book.py
xrocket/trade/orders.py
xrocket/trade/pairs.py
xrocket/trade/rates.py
xrocket/trade/time_series.py
xrocket-0.2.1.dist-info/LICENSE
xrocket-0.2.1.dist-info/WHEEL
xrocket-0.2.1.dist-info/METADATA
xrocket-0.2.1.dist-info/RECORD
