Metadata-Version: 2.1
Name: xrocket
Version: 0.2.1
Summary: xRocket Python SDK
Author: shibdev, vlad
Requires-Dist: httpx
Project-URL: Documentation, https://github.com/ClickoTON-Foundation/xrocket/
Project-URL: Homepage, https://github.com/ClickoTON-Foundation/xrocket/
Project-URL: Repository, https://github.com/ClickoTON-Foundation/xrocket/
